intraspector-0.1.0.dist-info/metadata.json
intraspector-0.1.0.dist-info/top_level.txt
intraspector-0.1.0.dist-info/METADATA
intraspector-0.1.0.dist-info/DESCRIPTION.rst
intraspector-0.1.0.dist-info/WHEEL
intraspector-0.1.0.dist-info/RECORD
intraspector/intraspector.py
intraspector/__init__.py
