Metadata-Version: 2.0
Name: intraspector
Version: 0.1.0
Summary: Intraspector decorator for python
Home-page: https://github.com/BespokeInsights/python-intraspector
Author: Aaron Hayes
Author-email: aaron.hayes92@gmail.com
License: MIT
Platform: UNKNOWN
